pretix_bounces/__init__.py
pretix_bounces/apps.py
pretix_bounces/models.py
pretix_bounces/signals.py
pretix_bounces/utils.py
pretix_bounces/locale/django.pot
pretix_bounces/locale/ar/LC_MESSAGES/django.mo
pretix_bounces/locale/ar/LC_MESSAGES/django.po
pretix_bounces/locale/ca/LC_MESSAGES/django.mo
pretix_bounces/locale/ca/LC_MESSAGES/django.po
pretix_bounces/locale/cs/LC_MESSAGES/django.mo
pretix_bounces/locale/cs/LC_MESSAGES/django.po
pretix_bounces/locale/da/LC_MESSAGES/django.mo
pretix_bounces/locale/da/LC_MESSAGES/django.po
pretix_bounces/locale/de/LC_MESSAGES/django.mo
pretix_bounces/locale/de/LC_MESSAGES/django.po
pretix_bounces/locale/de_Informal/.gitkeep
pretix_bounces/locale/de_Informal/LC_MESSAGES/django.mo
pretix_bounces/locale/de_Informal/LC_MESSAGES/django.po
pretix_bounces/locale/el/LC_MESSAGES/django.mo
pretix_bounces/locale/el/LC_MESSAGES/django.po
pretix_bounces/locale/es/LC_MESSAGES/django.mo
pretix_bounces/locale/es/LC_MESSAGES/django.po
pretix_bounces/locale/fi/LC_MESSAGES/django.mo
pretix_bounces/locale/fi/LC_MESSAGES/django.po
pretix_bounces/locale/fr/LC_MESSAGES/django.mo
pretix_bounces/locale/fr/LC_MESSAGES/django.po
pretix_bounces/locale/hr/LC_MESSAGES/django.mo
pretix_bounces/locale/hr/LC_MESSAGES/django.po
pretix_bounces/locale/it/LC_MESSAGES/django.mo
pretix_bounces/locale/it/LC_MESSAGES/django.po
pretix_bounces/locale/ja/LC_MESSAGES/django.mo
pretix_bounces/locale/ja/LC_MESSAGES/django.po
pretix_bounces/locale/lv/LC_MESSAGES/django.mo
pretix_bounces/locale/lv/LC_MESSAGES/django.po
pretix_bounces/locale/nl/LC_MESSAGES/django.mo
pretix_bounces/locale/nl/LC_MESSAGES/django.po
pretix_bounces/locale/nl_BE/LC_MESSAGES/django.mo
pretix_bounces/locale/nl_BE/LC_MESSAGES/django.po
pretix_bounces/locale/nl_Informal/LC_MESSAGES/django.mo
pretix_bounces/locale/nl_Informal/LC_MESSAGES/django.po
pretix_bounces/locale/pl/LC_MESSAGES/django.mo
pretix_bounces/locale/pl/LC_MESSAGES/django.po
pretix_bounces/locale/pl_Informal/LC_MESSAGES/django.mo
pretix_bounces-1.5.0.dist-info/LICENSE
pretix_bounces-1.5.0.dist-info/METADATA
pretix_bounces-1.5.0.dist-info/WHEEL
pretix_bounces-1.5.0.dist-info/entry_points.txt
pretix_bounces-1.5.0.dist-info/top_level.txt
pretix_bounces-1.5.0.dist-info/RECORD
