Metadata-Version: 2.1
Name: pretix-bounces
Version: 1.5.0
Summary: Allows automatic processing of bounces or automatic replies to emails sent by pretix.
Author-email: pretix team <support@pretix.eu>
Maintainer-email: pretix team <support@pretix.eu>
License: Copyright 2017 Raphael Michel
Project-URL: homepage, https://github.com/pretix/pretix-bounces
Keywords: pretix
Requires-Python: >=3.9
License-File: LICENSE
